proxidize_pt-1.0.8.dist-info/licenses/LICENSE
src/__init__.py
src/cli.py
src/config.py
src/main.py
src/proxy_tester.py
src/ui.py
src/utils.py
proxidize_pt-1.0.8.dist-info/METADATA
proxidize_pt-1.0.8.dist-info/WHEEL
proxidize_pt-1.0.8.dist-info/entry_points.txt
proxidize_pt-1.0.8.dist-info/top_level.txt
proxidize_pt-1.0.8.dist-info/RECORD
