Metadata-Version: 2.4
Name: proxidize_pt
Version: 1.0.8
Summary: Proxidize Proxy Tester - A multi-threaded proxy testing tool for HTTP/SOCKS proxies
Home-page: https://github.com/fawaz7/Proxy-tester
Author: Proxidize
Author-email: Proxidize <support@proxidize.com>
License: MIT
Project-URL: Homepage, https://github.com/fawaz7/Proxy-tester
Project-URL: Bug Reports, https://github.com/fawaz7/Proxy-tester/issues
Project-URL: Source, https://github.com/fawaz7/Proxy-tester
Project-URL: Documentation, https://github.com/fawaz7/Proxy-tester/wiki
Keywords: proxy,testing,http,socks,socks5,network,tool,multi-threaded
Platform: Windows
Platform: Linux
Platform: macOS
Platform: Unix
Classifier: Development Status :: 5 - Production/Stable
Classifier: Intended Audience :: Developers
Classifier: Intended Audience :: System Administrators
Classifier: License :: OSI Approved :: MIT License
Classifier: Operating System :: OS Independent
Classifier: Programming Language :: Python :: 3
Classifier: Programming Language :: Python :: 3.7
Classifier: Programming Language :: Python :: 3.8
Classifier: Programming Language :: Python :: 3.9
Classifier: Programming Language :: Python :: 3.10
Classifier: Programming Language :: Python :: 3.11
Classifier: Programming Language :: Python :: 3.12
Classifier: Programming Language :: Python :: 3.13
Classifier: Topic :: Internet :: Proxy Servers
Classifier: Topic :: System :: Networking
Classifier: Topic :: Software Development :: Testing
Classifier: Topic :: Utilities
Requires-Python: >=3.7
License-File: LICENSE
Requires-Dist: httpx[socks]>=0.25.0
Requires-Dist: rich>=13.0.0
Requires-Dist: requests>=2.28.0
Requires-Dist: pysocks>=1.7.1
Requires-Dist: pyfiglet>=0.8.0
Requires-Dist: colorama>=0.4.6
Requires-Dist: speedtest-cli>=2.1.3
Provides-Extra: dev
Requires-Dist: pytest>=7.0.0; extra == "dev"
Requires-Dist: pytest-cov>=4.0.0; extra == "dev"
Requires-Dist: black>=22.0.0; extra == "dev"
Requires-Dist: flake8>=5.0.0; extra == "dev"
Requires-Dist: mypy>=1.0.0; extra == "dev"
Provides-Extra: build
Requires-Dist: build>=0.8.0; extra == "build"
Requires-Dist: twine>=4.0.0; extra == "build"
Requires-Dist: wheel>=0.37.0; extra == "build"
Dynamic: author
Dynamic: home-page
Dynamic: license-file
Dynamic: platform
Dynamic: requires-python
